pywisdom/__init__.py
pywisdom/abheader.py
pywisdom/ablocus.py
pywisdom/abmatrix.py
pywisdom/absample.py
pywisdom-0.11.6.dist-info/METADATA
pywisdom-0.11.6.dist-info/WHEEL
pywisdom-0.11.6.dist-info/top_level.txt
pywisdom-0.11.6.dist-info/RECORD
