Metadata-Version: 2.1
Name: pywisdom
Version: 0.11.6
Summary: Python module to read and parse AB Matrix files
Author-email: Daniel Garrigan <daniel.garrigan@wisdompanel.com>
Project-URL: Homepage, https://gitlab.com/popgendad/pywisdom
Classifier: Development Status :: 4 - Beta
Classifier: Programming Language :: Python :: 3
Classifier: Operating System :: OS Independent
Classifier: Topic :: Software Development :: Libraries
Classifier: Topic :: Scientific/Engineering :: Bio-Informatics
Requires-Python: >=3.9
Requires-Dist: boto3>=1.26
